[{"id":"DRitJoNGTkHXZvH_YpLIAw","alias":"marc-forgione-new-york-2","name":"Marc Forgione","image_url":"https://s3-media3.fl.yelpcdn.com/bphoto/f_rrhoaW8XBineAC9IsVMA/o.jpg","is_closed":false,"url":"https://www.yelp.com/biz/marc-forgione-new-york-2?adjust_creative=JYD76SmnxEX58unWQnyhnA&utm_campaign=yelp_api_v3&utm_medium=api_v3_business_search&utm_source=JYD76SmnxEX58unWQnyhnA","review_count":1056,"categories":[{"alias":"newamerican","title":"New American"}],"rating":4.3,"coordinates":{"latitude":40.71667,"longitude":-74.00899},"transactions":["delivery","pickup"],"price":"$$$","location":{"address1":"30 Hudson St","address2":"","address3":"","city":"New York","zip_code":"10013","country":"US","state":"NY","display_address":["30 Hudson St","New York, NY 10013"]},"phone":"+12129419401","display_phone":"(212) 941-9401","distance":333.15979837915523,"business_hours":[{"open":[{"is_overnight":false,"start":"1700","end":"2130","day":0},{"is_overnight":false,"start":"1700","end":"2130","day":1},{"is_overnight":false,"start":"1700","end":"2130","day":2},{"is_overnight":false,"start":"1700","end":"2130","day":3},{"is_overnight":false,"start":"1700","end":"2200","day":4},{"is_overnight":false,"start":"1700","end":"2200","day":5}],"hours_type":"REGULAR","is_open_now":false}],"attributes":{"business_temp_closed":null,"menu_url":"http://www.marcforgione.com/menu/","open24_hours":null,"waitlist_reservation":null}},{"id":"__EvomQ2tE1NtkWn32WEXg","alias":"au-cheval-new-york-7","name":"Au Cheval","image_url":"https://s3-media1.fl.yelpcdn.com/bphoto/fvAzGG36LWddvyRulndBbw/o.jpg","is_closed":false,"url":"https://www.yelp.com/biz/au-cheval-new-york-7?adjust_creative=JYD76SmnxEX58unWQnyhnA&utm_campaign=yelp_api_v3&utm_medium=api_v3_business_search&utm_source=JYD76SmnxEX58unWQnyhnA","review_count":1176,"categories":[{"alias":"burgers","title":"Burgers"},{"alias":"newamerican","title":"New American"},{"alias":"cocktailbars","title":"Cocktail Bars"}],"rating":4.3,"coordinates":{"latitude":40.71812171604106,"longitude":-74.00196237391103},"transactions":[],"price":"$$$","location":{"address1":"33 Cortlandt Aly","address2":"","address3":null,"city":"New York","zip_code":"10013","country":"US","state":"NY","display_address":["33 Cortlandt Aly","New York, NY 10013"]},"phone":"+16463502429","display_phone":"(646) 350-2429","distance":288.93614204166096,"business_hours":[{"open":[{"is_overnight":false,"start":"1700","end":"2230","day":0},{"is_overnight":false,"start":"1700","end":"2230","day":1},{"is_overnight":false,"start":"1200","end":"2230","day":2},{"is_overnight":false,"start":"1200","end":"2230","day":3},{"is_overnight":false,"start":"1200","end":"2330","day":4},{"is_overnight":false,"start":"1100","end":"2330","day":5},{"is_overnight":false,"start":"1100","end":"2230","day":6}],"hours_type":"REGULAR","is_open_now":false}],"attributes":{"business_temp_closed":null,"menu_url":null,"open24_hours":null,"waitlist_reservation":null}},{"id":"fVsH6QIJPzXpVbgmeiolsA","alias":"jungsik-new-york","name":"Jungsik","image_url":"https://s3-media1.fl.yelpcdn.com/bphoto/O7GWZ_aclOrZiHZnPkWQaA/o.jpg","is_closed":false,"url":"https://www.yelp.com/biz/jungsik-new-york?adjust_creative=JYD76SmnxEX58unWQnyhnA&utm_campaign=yelp_api_v3&utm_medium=api_v3_business_search&utm_source=JYD76SmnxEX58unWQnyhnA","review_count":808,"categories":[{"alias":"korean","title":"Korean"}],"rating":4.6,"coordinates":{"latitude":40.7188032533572,"longitude":-74.0090829725856},"transactions":[],"price":"$$$$","location":{"address1":"2 Harrison St","address2":"","address3":"","city":"New York","zip_code":"10013","country":"US","state":"NY","display_address":["2 Harrison St","New York, NY 10013"]},"phone":"+12122190900","display_phone":"(212) 219-0900","distance":400.7051335524275,"business_hours":[{"open":[{"is_overnight":false,"start":"1700","end":"2100","day":1},{"is_overnight":false,"start":"1700","end":"2100","day":2},{"is_overnight":false,"start":"1700","end":"2100","day":3},{"is_overnight":false,"start":"1700","end":"2130","day":4},{"is_overnight":false,"start":"1700","end":"2130","day":5},{"is_overnight":false,"start":"1700","end":"2100","day":6}],"hours_type":"REGULAR","is_open_now":false}],"attributes":{"business_temp_closed":null,"menu_url":"http://jungsik.com/eat/","open24_hours":null,"waitlist_reservation":null}},{"id":"abNHO9-xlCsv31gghCUuxw","alias":"zutto-japanese-american-pub-new-york-2","name":"Zutto Japanese American Pub","image_url":"https://s3-media3.fl.yelpcdn.com/bphoto/kNweT2aeDRtRl65SJf-LWQ/o.jpg","is_closed":false,"url":"https://www.yelp.com/biz/zutto-japanese-american-pub-new-york-2?adjust_creative=JYD76SmnxEX58unWQnyhnA&utm_campaign=yelp_api_v3&utm_medium=api_v3_business_search&utm_source=JYD76SmnxEX58unWQnyhnA","review_count":1140,"categories":[{"alias":"sushi","title":"Sushi Bars"},{"alias":"ramen","title":"Ramen"},{"alias":"cocktailbars","title":"Cocktail Bars"}],"rating":4,"coordinates":{"latitude":40.71847,"longitude":-74.00903},"transactions":["delivery","pickup"],"price":"$$","location":{"address1":"77 Hudson St","address2":null,"address3":"","city":"New York","zip_code":"10013","country":"US","state":"NY","display_address":["77 Hudson St","New York, NY 10013"]},"phone":"+12122333287","display_phone":"(212) 233-3287","distance":384.53422967069423,"business_hours":[{"open":[{"is_overnight":false,"start":"1130","end":"2200","day":0},{"is_overnight":false,"start":"1130","end":"2200","day":1},{"is_overnight":false,"start":"1130","end":"2200","day":2},{"is_overnight":false,"start":"1130","end":"2200","day":3},{"is_overnight":false,"start":"1130","end":"2300","day":4},{"is_overnight":false,"start":"1200","end":"2300","day":5},{"is_overnight":false,"start":"1200","end":"2200","day":6}],"hours_type":"REGULAR","is_open_now":false}],"attributes":{"business_temp_closed":null,"menu_url":"https://zuttonyc.com/tribeca-food-menu/","open24_hours":null,"waitlist_reservation":true}},{"id":"2Nwmd7-1d1rI6lb9QSSYYA","alias":"a-pasta-bar-new-york","name":"A Pasta Bar","image_url":"https://s3-media2.fl.yelpcdn.com/bphoto/yBcgO4-xpz3KZDZQBpK1SQ/o.jpg","is_closed":false,"url":"https://www.yelp.com/biz/a-pasta-bar-new-york?adjust_creative=JYD76SmnxEX58unWQnyhnA&utm_campaign=yelp_api_v3&utm_medium=api_v3_business_search&utm_source=JYD76SmnxEX58unWQnyhnA","review_count":631,"categories":[{"alias":"italian","title":"Italian"},{"alias":"bars","title":"Bars"}],"rating":4,"coordinates":{"latitude":40.72229,"longitude":-74.00403},"transactions":["delivery","pickup"],"price":"$$$","location":{"address1":"330 W Broadway","address2":"","address3":null,"city":"New York","zip_code":"10013","country":"US","state":"NY","display_address":["330 W Broadway","New York, NY 10013"]},"phone":"+16467624056","display_phone":"(646) 762-4056","distance":603.1501337019138,"business_hours":[{"open":[{"is_overnight":false,"start":"1700","end":"2300","day":0},{"is_overnight":false,"start":"1700","end":"2300","day":1},{"is_overnight":false,"start":"1700","end":"2300","day":2},{"is_overnight":false,"start":"1200","end":"2300","day":3},{"is_overnight":false,"start":"1200","end":"2330","day":4},{"is_overnight":false,"start":"1200","end":"2330","day":5},{"is_overnight":false,"start":"1200","end":"2300","day":6}],"hours_type":"REGULAR","is_open_now":true}],"attributes":{"business_temp_closed":null,"menu_url":"http://apastabar.com/menu/","open24_hours":null,"waitlist_reservation":null}},{"id":"SXWnyFNLCehVlJPRxk7gAg","alias":"anejo-tribeca-new-york-3","name":"Anejo Tribeca","image_url":"https://s3-media2.fl.yelpcdn.com/bphoto/Ioqom9jux9mVLAEDehphPw/o.jpg","is_closed":false,"url":"https://www.yelp.com/biz/anejo-tribeca-new-york-3?adjust_creative=JYD76SmnxEX58unWQnyhnA&utm_campaign=yelp_api_v3&utm_medium=api_v3_business_search&utm_source=JYD76SmnxEX58unWQnyhnA","review_count":738,"categories":[{"alias":"mexican","title":"Mexican"},{"alias":"tapasmallplates","title":"Tapas/Small Plates"},{"alias":"tapas","title":"Tapas Bars"}],"rating":4.1,"coordinates":{"latitude":40.71931499731559,"longitude":-74.00427174111186},"transactions":["delivery","pickup"],"price":"$$","location":{"address1":"301 Church St","address2":"","address3":"","city":"New York","zip_code":"10013","country":"US","state":"NY","display_address":["301 Church St","New York, NY 10013"]},"phone":"+12129206270","display_phone":"(212) 920-6270","distance":271.5840186465169,"business_hours":[{"open":[{"is_overnight":false,"start":"1200","end":"2300","day":0},{"is_overnight":false,"start":"1200","end":"2300","day":1},{"is_overnight":false,"start":"1200","end":"2300","day":2},{"is_overnight":false,"start":"1200","end":"0000","day":3},{"is_overnight":false,"start":"1200","end":"0000","day":4},{"is_overnight":false,"start":"1130","end":"0000","day":5},{"is_overnight":false,"start":"1130","end":"2100","day":6}],"hours_type":"REGULAR","is_open_now":true}],"attributes":{"business_temp_closed":null,"menu_url":"http://anejotribeca.com/images/foodmenu.jpg","open24_hours":null,"waitlist_reservation":true}},{"id":"U74_3F7r3tMhd6dmTmDBxQ","alias":"macao-trading-company-new-york","name":"Macao Trading Company","image_url":"https://s3-media2.fl.yelpcdn.com/bphoto/a42HwkzaE-er3Es6rZ9K9w/o.jpg","is_closed":false,"url":"https://www.yelp.com/biz/macao-trading-company-new-york?adjust_creative=JYD76SmnxEX58unWQnyhnA&utm_campaign=yelp_api_v3&utm_medium=api_v3_business_search&utm_source=JYD76SmnxEX58unWQnyhnA","review_count":908,"categories":[{"alias":"asianfusion","title":"Asian Fusion"},{"alias":"portuguese","title":"Portuguese"},{"alias":"chinese","title":"Chinese"}],"rating":3.8,"coordinates":{"latitude":40.719623,"longitude":-74.003904},"transactions":["delivery","pickup"],"price":"$$$","location":{"address1":"311 Church St","address2":"","address3":"","city":"New York","zip_code":"10013","country":"US","state":"NY","display_address":["311 Church St","New York, NY 10013"]},"phone":"+12124318642","display_phone":"(212) 431-8642","distance":313.6050941846996,"business_hours":[{"open":[{"is_overnight":false,"start":"1700","end":"0000","day":0},{"is_overnight":true,"start":"1700","end":"0200","day":1},{"is_overnight":true,"start":"1700","end":"0200","day":2},{"is_overnight":true,"start":"1700","end":"0400","day":3},{"is_overnight":true,"start":"1700","end":"0400","day":4},{"is_overnight":true,"start":"1700","end":"0400","day":5},{"is_overnight":false,"start":"1700","end":"0000","day":6}],"hours_type":"REGULAR","is_open_now":true}],"attributes":{"business_temp_closed":null,"menu_url":"https://www.macaonyc.com/menus/","open24_hours":null,"waitlist_reservation":null}},{"id":"d-DQwNxs77Pah2ys0q7w1Q","alias":"american-cut-steakhouse-tribeca-new-york","name":"American Cut Steakhouse Tribeca","image_url":"https://s3-media2.fl.yelpcdn.com/bphoto/YTGiIp38Tff9xjPS92YC2w/o.jpg","is_closed":false,"url":"https://www.yelp.com/biz/american-cut-steakhouse-tribeca-new-york?adjust_creative=JYD76SmnxEX58unWQnyhnA&utm_campaign=yelp_api_v3&utm_medium=api_v3_business_search&utm_source=JYD76SmnxEX58unWQnyhnA","review_count":694,"categories":[{"alias":"steak","title":"Steakhouses"},{"alias":"newamerican","title":"New American"},{"alias":"venues","title":"Venues & Event Spaces"}],"rating":3.9,"coordinates":{"latitude":40.71915,"longitude":-74.00994},"transactions":["delivery"],"price":"$$$$","location":{"address1":"363 Greenwich St","address2":"","address3":"","city":"New York","zip_code":"10013","country":"US","state":"NY","display_address":["363 Greenwich St","New York, NY 10013"]},"phone":"+12122264736","display_phone":"(212) 226-4736","distance":484.88266894482024,"business_hours":[{"open":[{"is_overnight":false,"start":"1700","end":"2100","day":0},{"is_overnight":false,"start":"1700","end":"2100","day":1},{"is_overnight":false,"start":"1700","end":"2100","day":2},{"is_overnight":false,"start":"1700","end":"2100","day":3},{"is_overnight":false,"start":"1700","end":"2200","day":4},{"is_overnight":false,"start":"1700","end":"2200","day":5}],"hours_type":"REGULAR","is_open_now":false}],"attributes":{"business_temp_closed":null,"menu_url":"https://www.americancutsteakhouse.com/location/american-cut-tribeca/#first-course","open24_hours":null,"waitlist_reservation":null}},{"id":"liZmIO0FqZwslLJfLDkfgw","alias":"wayla-new-york","name":"Wayla","image_url":"https://s3-media2.fl.yelpcdn.com/bphoto/u17PWWBYzqe3p1uEPgKVuQ/o.jpg","is_closed":false,"url":"https://www.yelp.com/biz/wayla-new-york?adjust_creative=JYD76SmnxEX58unWQnyhnA&utm_campaign=yelp_api_v3&utm_medium=api_v3_business_search&utm_source=JYD76SmnxEX58unWQnyhnA","review_count":728,"categories":[{"alias":"thai","title":"Thai"}],"rating":4.4,"coordinates":{"latitude":40.7183,"longitude":-73.9926038},"transactions":["delivery"],"price":"$$$","location":{"address1":"100 Forsyth St","address2":"Basement","address3":null,"city":"New York","zip_code":"10002","country":"US","state":"NY","display_address":["100 Forsyth St","Basement","New York, NY 10002"]},"phone":"+12122062500","display_phone":"(212) 206-2500","distance":1056.8612324633887,"business_hours":[{"open":[{"is_overnight":false,"start":"1200","end":"1500","day":0},{"is_overnight":false,"start":"1700","end":"2230","day":0},{"is_overnight":false,"start":"1200","end":"1500","day":1},{"is_overnight":false,"start":"1700","end":"2230","day":1},{"is_overnight":false,"start":"1200","end":"1500","day":2},{"is_overnight":false,"start":"1700","end":"2230","day":2},{"is_overnight":false,"start":"1200","end":"1500","day":3},{"is_overnight":false,"start":"1700","end":"2300","day":3},{"is_overnight":false,"start":"1200","end":"1500","day":4},{"is_overnight":false,"start":"1700","end":"2300","day":4},{"is_overnight":false,"start":"1200","end":"1500","day":5},{"is_overnight":false,"start":"1700","end":"2300","day":5},{"is_overnight":false,"start":"1200","end":"1500","day":6},{"is_overnight":false,"start":"1700","end":"2230","day":6}],"hours_type":"REGULAR","is_open_now":false}],"attributes":{"business_temp_closed":null,"menu_url":null,"open24_hours":null,"waitlist_reservation":null}},{"id":"ja--tSqGBMm6ueiN96woLQ","alias":"filé-gumbo-bar-new-york","name":"Filé Gumbo Bar","image_url":"https://s3-media1.fl.yelpcdn.com/bphoto/NtaJeaiCpSNx2VAA_yjFAA/o.jpg","is_closed":false,"url":"https://www.yelp.com/biz/fil%C3%A9-gumbo-bar-new-york?adjust_creative=JYD76SmnxEX58unWQnyhnA&utm_campaign=yelp_api_v3&utm_medium=api_v3_business_search&utm_source=JYD76SmnxEX58unWQnyhnA","review_count":267,"categories":[{"alias":"cajun","title":"Cajun/Creole"},{"alias":"venues","title":"Venues & Event Spaces"},{"alias":"cocktailbars","title":"Cocktail Bars"}],"rating":4,"coordinates":{"latitude":40.71850573859628,"longitude":-74.0048807036876},"transactions":["delivery","pickup"],"price":"$$$","location":{"address1":"275 Church St","address2":null,"address3":"","city":"New York","zip_code":"10013","country":"US","state":"NY","display_address":["275 Church St","New York, NY 10013"]},"phone":"+16468510810","display_phone":"(646) 851-0810","distance":174.64923677665877,"business_hours":[{"open":[{"is_overnight":false,"start":"1130","end":"2130","day":0},{"is_overnight":false,"start":"1130","end":"2130","day":1},{"is_overnight":false,"start":"1130","end":"2130","day":2},{"is_overnight":false,"start":"1130","end":"2130","day":3},{"is_overnight":true,"start":"1130","end":"0100","day":4},{"is_overnight":false,"start":"1130","end":"2300","day":5},{"is_overnight":false,"start":"1130","end":"2130","day":6}],"hours_type":"REGULAR","is_open_now":false}],"attributes":{"business_temp_closed":null,"menu_url":"https://www.filenyc.com/menus","open24_hours":null,"waitlist_reservation":null}},{"id":"WYhRkUATHRyXZrE55MArbA","alias":"scalini-fedeli-new-york","name":"Scalini Fedeli","image_url":"https://s3-media3.fl.yelpcdn.com/bphoto/WxrAnaPADiHlAQZfDrAYfg/o.jpg","is_closed":false,"url":"https://www.yelp.com/biz/scalini-fedeli-new-york?adjust_creative=JYD76SmnxEX58unWQnyhnA&utm_campaign=yelp_api_v3&utm_medium=api_v3_business_search&utm_source=JYD76SmnxEX58unWQnyhnA","review_count":386,"categories":[{"alias":"italian","title":"Italian"}],"rating":4.4,"coordinates":{"latitude":40.71741473500126,"longitude":-74.00943235989747},"transactions":["pickup"],"price":"$$$$","location":{"address1":"165 Duane St","address2":"","address3":"","city":"New York","zip_code":"10013","country":"US","state":"NY","display_address":["165 Duane St","New York, NY 10013"]},"phone":"+12125280400","display_phone":"(212) 528-0400","distance":376.0743974153157,"business_hours":[{"open":[{"is_overnight":false,"start":"1730","end":"2100","day":1},{"is_overnight":false,"start":"1730","end":"2100","day":2},{"is_overnight":false,"start":"1730","end":"2100","day":3},{"is_overnight":false,"start":"1730","end":"2200","day":4},{"is_overnight":false,"start":"1730","end":"2200","day":5},{"is_overnight":false,"start":"1630","end":"2030","day":6}],"hours_type":"REGULAR","is_open_now":false}],"attributes":{"business_temp_closed":null,"menu_url":"http://www.scalinifedeli.com/tribeca/menus","open24_hours":null,"waitlist_reservation":null}},{"id":"FiRB9Ek3Xo9JHwXgBYITYg","alias":"la-sirene-new-york-4","name":"La Sirene","image_url":"https://s3-media4.fl.yelpcdn.com/bphoto/dSWCdLWNmYdpim8ijCpO7Q/o.jpg","is_closed":false,"url":"https://www.yelp.com/biz/la-sirene-new-york-4?adjust_creative=JYD76SmnxEX58unWQnyhnA&utm_campaign=yelp_api_v3&utm_medium=api_v3_business_search&utm_source=JYD76SmnxEX58unWQnyhnA","review_count":1757,"categories":[{"alias":"french","title":"French"},{"alias":"wine_bars","title":"Wine Bars"},{"alias":"fondue","title":"Fondue"}],"rating":4.3,"coordinates":{"latitude":40.7243642217227,"longitude":-74.005708694458},"transactions":["delivery","pickup"],"price":"$$$","location":{"address1":"558 Broome St","address2":"","address3":"","city":"New York","zip_code":"10013","country":"US","state":"NY","display_address":["558 Broome St","New York, NY 10013"]},"phone":"+12129253061","display_phone":"(212) 925-3061","distance":827.7866758780423,"business_hours":[{"open":[{"is_overnight":false,"start":"1600","end":"2200","day":0},{"is_overnight":false,"start":"1600","end":"2200","day":1},{"is_overnight":false,"start":"1600","end":"2200","day":2},{"is_overnight":false,"start":"1600","end":"2200","day":3},{"is_overnight":false,"start":"1600","end":"2315","day":4},{"is_overnight":false,"start":"1600","end":"2315","day":5},{"is_overnight":false,"start":"1600","end":"2200","day":6}],"hours_type":"REGULAR","is_open_now":false}],"attributes":{"business_temp_closed":null,"menu_url":"https://lasirenenyc.com/soho-menu/","open24_hours":null,"waitlist_reservation":true}},{"id":"f8ipr8Wdy1_wHhw7JgNqPQ","alias":"da-claudio-new-york","name":"Da Claudio","image_url":"https://s3-media1.fl.yelpcdn.com/bphoto/Pr50AvB9BqPTqmqTAyUVsA/o.jpg","is_closed":false,"url":"https://www.yelp.com/biz/da-claudio-new-york?adjust_creative=JYD76SmnxEX58unWQnyhnA&utm_campaign=yelp_api_v3&utm_medium=api_v3_business_search&utm_source=JYD76SmnxEX58unWQnyhnA","review_count":682,"categories":[{"alias":"italian","title":"Italian"},{"alias":"cocktailbars","title":"Cocktail Bars"},{"alias":"seafood","title":"Seafood"}],"rating":4.3,"coordinates":{"latitude":40.71087,"longitude":-74.00753},"transactions":["delivery","pickup","restaurant_reservation"],"price":"$$$","location":{"address1":"21 Ann St","address2":"","address3":"","city":"New York","zip_code":"10038","country":"US","state":"NY","display_address":["21 Ann St","New York, NY 10038"]},"phone":"+12122852668","display_phone":"(212) 285-2668","distance":702.1335598521766,"business_hours":[{"open":[{"is_overnight":false,"start":"1130","end":"1500","day":0},{"is_overnight":false,"start":"1700","end":"2130","day":0},{"is_overnight":false,"start":"1130","end":"1500","day":1},{"is_overnight":false,"start":"1700","end":"2130","day":1},{"is_overnight":false,"start":"1130","end":"1500","day":2},{"is_overnight":false,"start":"1700","end":"2130","day":2},{"is_overnight":false,"start":"1130","end":"1500","day":3},{"is_overnight":false,"start":"1700","end":"2130","day":3},{"is_overnight":false,"start":"1700","end":"2130","day":4},{"is_overnight":false,"start":"1700","end":"2130","day":5},{"is_overnight":false,"start":"1700","end":"2130","day":6}],"hours_type":"REGULAR","is_open_now":false}],"attributes":{"business_temp_closed":null,"menu_url":"https://s3.amazonaws.com/daclaudionyc/daclaudio_menu_dinner_spring_2020-1585332247938.pdf","open24_hours":null,"waitlist_reservation":true}},{"id":"Lp8vAE5nHSt5zbu-lSGK8A","alias":"hop-lee-restaurant-new-york","name":"Hop Lee Restaurant","image_url":"https://s3-media1.fl.yelpcdn.com/bphoto/B-i_n294Kb7Po8aUlaqubw/o.jpg","is_closed":false,"url":"https://www.yelp.com/biz/hop-lee-restaurant-new-york?adjust_creative=JYD76SmnxEX58unWQnyhnA&utm_campaign=yelp_api_v3&utm_medium=api_v3_business_search&utm_source=JYD76SmnxEX58unWQnyhnA","review_count":418,"categories":[{"alias":"chinese","title":"Chinese"},{"alias":"seafood","title":"Seafood"},{"alias":"noodles","title":"Noodles"}],"rating":3.9,"coordinates":{"latitude":40.71422,"longitude":-73.99864},"transactions":["delivery"],"price":"$$","location":{"address1":"16 Mott St","address2":"","address3":"","city":"New York","zip_code":"10013","country":"US","state":"NY","display_address":["16 Mott St","New York, NY 10013"]},"phone":"+12129626475","display_phone":"(212) 962-6475","distance":614.5585922812679,"business_hours":[{"open":[{"is_overnight":false,"start":"1100","end":"0000","day":0},{"is_overnight":false,"start":"1100","end":"0000","day":1},{"is_overnight":false,"start":"1100","end":"0000","day":2},{"is_overnight":false,"start":"1100","end":"0000","day":3},{"is_overnight":false,"start":"1100","end":"0000","day":4},{"is_overnight":false,"start":"1100","end":"0000","day":5},{"is_overnight":false,"start":"1100","end":"0000","day":6}],"hours_type":"REGULAR","is_open_now":true}],"attributes":{"business_temp_closed":null,"menu_url":null,"open24_hours":null,"waitlist_reservation":null}},{"id":"X8ZS-dgiMIJvhwf9SaDnjw","alias":"wah-fung-no-1-new-york-2","name":"Wah Fung No 1","image_url":"https://s3-media1.fl.yelpcdn.com/bphoto/KneHCoY6vhFMcQ6ZWZ0J3g/o.jpg","is_closed":false,"url":"https://www.yelp.com/biz/wah-fung-no-1-new-york-2?adjust_creative=JYD76SmnxEX58unWQnyhnA&utm_campaign=yelp_api_v3&utm_medium=api_v3_business_search&utm_source=JYD76SmnxEX58unWQnyhnA","review_count":2274,"categories":[{"alias":"hotdogs","title":"Fast Food"},{"alias":"cantonese","title":"Cantonese"}],"rating":4.4,"coordinates":{"latitude":40.71735,"longitude":-73.99457},"transactions":["delivery"],"price":"$","location":{"address1":"79 Chrystie St","address2":"","address3":"","city":"New York","zip_code":"10002","country":"US","state":"NY","display_address":["79 Chrystie St","New York, NY 10002"]},"phone":"+12129255175","display_phone":"(212) 925-5175","distance":882.5900126332134,"business_hours":[{"open":[{"is_overnight":false,"start":"0900","end":"1900","day":1},{"is_overnight":false,"start":"0900","end":"1900","day":2},{"is_overnight":false,"start":"0900","end":"1900","day":3},{"is_overnight":false,"start":"0900","end":"1900","day":4},{"is_overnight":false,"start":"0900","end":"1900","day":5},{"is_overnight":false,"start":"0900","end":"1900","day":6}],"hours_type":"REGULAR","is_open_now":false}],"attributes":{"business_temp_closed":null,"menu_url":"https://wah-fung.com/menu","open24_hours":null,"waitlist_reservation":null}},{"id":"FgPvSR_42MtGKy0_n055iw","alias":"double-chicken-please-new-york","name":"Double Chicken Please","image_url":"https://s3-media2.fl.yelpcdn.com/bphoto/C02s75JQEcob9WVXTIDDnQ/o.jpg","is_closed":false,"url":"https://www.yelp.com/biz/double-chicken-please-new-york?adjust_creative=JYD76SmnxEX58unWQnyhnA&utm_campaign=yelp_api_v3&utm_medium=api_v3_business_search&utm_source=JYD76SmnxEX58unWQnyhnA","review_count":801,"categories":[{"alias":"cocktailbars","title":"Cocktail Bars"},{"alias":"burgers","title":"Burgers"},{"alias":"sandwiches","title":"Sandwiches"}],"rating":4.4,"coordinates":{"latitude":40.719584,"longitude":-73.990486},"transactions":["delivery","pickup"],"price":"$$$","location":{"address1":"115 Allen St","address2":null,"address3":"","city":"New York","zip_code":"10002","country":"US","state":"NY","display_address":["115 Allen St","New York, NY 10002"]},"phone":"+16466785452","display_phone":"(646) 678-5452","distance":1250.16299226979,"business_hours":[{"open":[{"is_overnight":true,"start":"1700","end":"0100","day":1},{"is_overnight":true,"start":"1700","end":"0100","day":2},{"is_overnight":true,"start":"1700","end":"0100","day":3},{"is_overnight":true,"start":"1700","end":"0130","day":4},{"is_overnight":true,"start":"1700","end":"0130","day":5},{"is_overnight":false,"start":"1700","end":"0000","day":6}],"hours_type":"REGULAR","is_open_now":false}],"attributes":{"business_temp_closed":null,"menu_url":null,"open24_hours":null,"waitlist_reservation":null}},{"id":"d7Asc4q2ImoPlA_BhfroTQ","alias":"kesté-pizza-and-vino-new-york-5","name":"Kesté Pizza & Vino","image_url":"https://s3-media1.fl.yelpcdn.com/bphoto/Dd5EOBOvbRs5ttjQwuJedQ/o.jpg","is_closed":false,"url":"https://www.yelp.com/biz/kest%C3%A9-pizza-and-vino-new-york-5?adjust_creative=JYD76SmnxEX58unWQnyhnA&utm_campaign=yelp_api_v3&utm_medium=api_v3_business_search&utm_source=JYD76SmnxEX58unWQnyhnA","review_count":1975,"categories":[{"alias":"pizza","title":"Pizza"},{"alias":"italian","title":"Italian"},{"alias":"wine_bars","title":"Wine Bars"}],"rating":4.2,"coordinates":{"latitude":40.709135,"longitude":-74.004645},"transactions":["delivery","pickup","restaurant_reservation"],"price":"$$","location":{"address1":"77 Fulton St","address2":"","address3":"","city":"New York","zip_code":"10038","country":"US","state":"NY","display_address":["77 Fulton St","New York, NY 10038"]},"phone":"+12122431500","display_phone":"(212) 243-1500","distance":874.9320030926298,"business_hours":[{"open":[{"is_overnight":false,"start":"1100","end":"2130","day":0},{"is_overnight":false,"start":"1100","end":"2130","day":1},{"is_overnight":false,"start":"1100","end":"2130","day":2},{"is_overnight":false,"start":"1100","end":"2130","day":3},{"is_overnight":false,"start":"1100","end":"2230","day":4},{"is_overnight":false,"start":"1100","end":"2230","day":5},{"is_overnight":false,"start":"1100","end":"2130","day":6}],"hours_type":"REGULAR","is_open_now":false}],"attributes":{"business_temp_closed":null,"menu_url":"https://kestepizzeria.com/menu/","open24_hours":null,"waitlist_reservation":null}},{"id":"nAcVK-Y1_ojsRF_04o-x-A","alias":"yin-ji-chang-fen-rice-roll-new-york","name":"Yin Ji Chang Fen Rice Roll","image_url":"https://s3-media2.fl.yelpcdn.com/bphoto/7ZNL4ngrm9KX6eWq0wx9kg/o.jpg","is_closed":false,"url":"https://www.yelp.com/biz/yin-ji-chang-fen-rice-roll-new-york?adjust_creative=JYD76SmnxEX58unWQnyhnA&utm_campaign=yelp_api_v3&utm_medium=api_v3_business_search&utm_source=JYD76SmnxEX58unWQnyhnA","review_count":504,"categories":[{"alias":"breakfast_brunch","title":"Breakfast & Brunch"},{"alias":"dimsum","title":"Dim Sum"},{"alias":"cantonese","title":"Cantonese"}],"rating":4.1,"coordinates":{"latitude":40.71583,"longitude":-73.999336},"transactions":["delivery","pickup"],"price":"$$","location":{"address1":"91 Bayard St","address2":"","address3":null,"city":"New York","zip_code":"10013","country":"US","state":"NY","display_address":["91 Bayard St","New York, NY 10013"]},"phone":"+12122274888","display_phone":"(212) 227-4888","distance":494.2039625257383,"business_hours":[{"open":[{"is_overnight":false,"start":"0900","end":"2045","day":0},{"is_overnight":false,"start":"0900","end":"2045","day":1},{"is_overnight":false,"start":"0900","end":"2045","day":2},{"is_overnight":false,"start":"0900","end":"2045","day":3},{"is_overnight":false,"start":"0900","end":"2045","day":4},{"is_overnight":false,"start":"0900","end":"2045","day":5},{"is_overnight":false,"start":"0900","end":"2045","day":6}],"hours_type":"REGULAR","is_open_now":false}],"attributes":{"business_temp_closed":null,"menu_url":null,"open24_hours":null,"waitlist_reservation":null}},{"id":"QbrxrDFR7emcmg-niMTfew","alias":"kyuramen-chinatown-new-york-3","name":"Kyuramen - Chinatown","image_url":"https://s3-media4.fl.yelpcdn.com/bphoto/hfsByVEWJLL1aeeC6oAACw/o.jpg","is_closed":false,"url":"https://www.yelp.com/biz/kyuramen-chinatown-new-york-3?adjust_creative=JYD76SmnxEX58unWQnyhnA&utm_campaign=yelp_api_v3&utm_medium=api_v3_business_search&utm_source=JYD76SmnxEX58unWQnyhnA","review_count":436,"categories":[{"alias":"ramen","title":"Ramen"},{"alias":"japacurry","title":"Japanese Curry"}],"rating":4.3,"coordinates":{"latitude":40.71896322342889,"longitude":-73.9948757},"transactions":["delivery","pickup","restaurant_reservation"],"price":"$$","location":{"address1":"132 Bowery","address2":"","address3":null,"city":"New York","zip_code":"10013","country":"US","state":"NY","display_address":["132 Bowery","New York, NY 10013"]},"phone":"+19176883166","display_phone":"(917) 688-3166","distance":883.6495299405369,"business_hours":[{"open":[{"is_overnight":false,"start":"1130","end":"2230","day":0},{"is_overnight":false,"start":"1130","end":"2230","day":1},{"is_overnight":false,"start":"1130","end":"2230","day":2},{"is_overnight":false,"start":"1130","end":"2230","day":3},{"is_overnight":false,"start":"1130","end":"2230","day":4},{"is_overnight":false,"start":"1130","end":"2230","day":5},{"is_overnight":false,"start":"1130","end":"2230","day":6}],"hours_type":"REGULAR","is_open_now":false}],"attributes":{"business_temp_closed":null,"menu_url":"https://www.kyuramen.com/menu","open24_hours":null,"waitlist_reservation":true}},{"id":"0GftSP2dRwEzujkv2VKIgA","alias":"wok-wok-southeast-asian-kitchen-new-york","name":"Wok Wok Southeast Asian Kitchen","image_url":"https://s3-media3.fl.yelpcdn.com/bphoto/XOc7n_rq6kYGXySwasouRQ/o.jpg","is_closed":false,"url":"https://www.yelp.com/biz/wok-wok-southeast-asian-kitchen-new-york?adjust_creative=JYD76SmnxEX58unWQnyhnA&utm_campaign=yelp_api_v3&utm_medium=api_v3_business_search&utm_source=JYD76SmnxEX58unWQnyhnA","review_count":1260,"categories":[{"alias":"chinese","title":"Chinese"},{"alias":"malaysian","title":"Malaysian"},{"alias":"thai","title":"Thai"}],"rating":4,"coordinates":{"latitude":40.7140555,"longitude":-73.9988387116394},"transactions":["delivery","pickup"],"price":"$$","location":{"address1":"11 Mott St","address2":null,"address3":"","city":"New York","zip_code":"10013","country":"US","state":"NY","display_address":["11 Mott St","New York, NY 10013"]},"phone":"+19173883627","display_phone":"(917) 388-3627","distance":611.2995502701872,"business_hours":[{"open":[{"is_overnight":false,"start":"1100","end":"2100","day":1},{"is_overnight":false,"start":"1100","end":"2100","day":2},{"is_overnight":false,"start":"1100","end":"2100","day":3},{"is_overnight":false,"start":"1100","end":"2100","day":4},{"is_overnight":false,"start":"1100","end":"2100","day":5},{"is_overnight":false,"start":"1100","end":"2100","day":6}],"hours_type":"REGULAR","is_open_now":false}],"attributes":{"business_temp_closed":null,"menu_url":"https://ilovewokwok.com/menu?location=ilovewokwok","open24_hours":null,"waitlist_reservation":null}}]