[{"id":"tnxb_qM5e7J5wIfYwJB3Ig","alias":"the-elgin-new-york","name":"The Elgin","image_url":"https://s3-media3.fl.yelpcdn.com/bphoto/7iO7wvyuE0e-_WBTtOT7Ww/o.jpg","is_closed":false,"url":"https://www.yelp.com/biz/the-elgin-new-york?adjust_creative=JYD76SmnxEX58unWQnyhnA&utm_campaign=yelp_api_v3&utm_medium=api_v3_business_search&utm_source=JYD76SmnxEX58unWQnyhnA","review_count":370,"categories":[{"alias":"cocktailbars","title":"Cocktail Bars"},{"alias":"beerbar","title":"Beer Bar"},{"alias":"newamerican","title":"New American"}],"rating":4.3,"coordinates":{"latitude":40.758339026848695,"longitude":-73.98082697379752},"transactions":["pickup","delivery"],"price":"$$$","location":{"address1":"64 West 48th St","address2":null,"address3":"","city":"New York","zip_code":"10036","country":"US","state":"NY","display_address":["64 West 48th St","New York, NY 10036"]},"phone":"+12122212100","display_phone":"(212) 221-2100","distance":4579.479533374004,"business_hours":[{"open":[{"is_overnight":false,"start":"1100","end":"2300","day":0},{"is_overnight":false,"start":"1100","end":"0000","day":1},{"is_overnight":false,"start":"1100","end":"0000","day":2},{"is_overnight":false,"start":"1100","end":"0000","day":3},{"is_overnight":false,"start":"1100","end":"0000","day":4},{"is_overnight":false,"start":"1100","end":"2300","day":5},{"is_overnight":false,"start":"1100","end":"2200","day":6}],"hours_type":"REGULAR","is_open_now":false}],"attributes":{"business_temp_closed":null,"menu_url":null,"open24_hours":null,"waitlist_reservation":null}},{"id":"jfnDwWBGK4JoWE5jbeKxSw","alias":"chu-ros-thai-new-york","name":"Chu Ros Thai","image_url":"https://s3-media2.fl.yelpcdn.com/bphoto/hJ3eqYLETJhMf6P6zdSmfA/o.jpg","is_closed":false,"url":"https://www.yelp.com/biz/chu-ros-thai-new-york?adjust_creative=JYD76SmnxEX58unWQnyhnA&utm_campaign=yelp_api_v3&utm_medium=api_v3_business_search&utm_source=JYD76SmnxEX58unWQnyhnA","review_count":238,"categories":[{"alias":"thai","title":"Thai"},{"alias":"asianfusion","title":"Asian Fusion"},{"alias":"desserts","title":"Desserts"}],"rating":4.5,"coordinates":{"latitude":40.78922,"longitude":-73.94873},"transactions":["pickup","delivery"],"price":"$$","location":{"address1":"1590 Lexington Ave","address2":null,"address3":"","city":"New York","zip_code":"10029","country":"US","state":"NY","display_address":["1590 Lexington Ave","New York, NY 10029"]},"phone":"+19172658432","display_phone":"(917) 265-8432","distance":1845.9012338178077,"business_hours":[{"open":[{"is_overnight":false,"start":"1045","end":"2200","day":0},{"is_overnight":false,"start":"1045","end":"2200","day":1},{"is_overnight":false,"start":"1045","end":"2200","day":2},{"is_overnight":false,"start":"1030","end":"2200","day":3},{"is_overnight":false,"start":"1045","end":"2200","day":4},{"is_overnight":false,"start":"1115","end":"2200","day":5},{"is_overnight":false,"start":"1115","end":"2200","day":6}],"hours_type":"REGULAR","is_open_now":false}],"attributes":{"business_temp_closed":null,"menu_url":"https://churosthainyc.com/new-york-east-harlem-upper-east-side-chu-ros-thai-food-menu","open24_hours":null,"waitlist_reservation":null}},{"id":"GXh9YpX4v8Wemrq-SPDPhA","alias":"es-bar-new-york","name":"e's BAR","image_url":"https://s3-media2.fl.yelpcdn.com/bphoto/s_n3rI6L-ga4FhZimQPOPA/o.jpg","is_closed":false,"url":"https://www.yelp.com/biz/es-bar-new-york?adjust_creative=JYD76SmnxEX58unWQnyhnA&utm_campaign=yelp_api_v3&utm_medium=api_v3_business_search&utm_source=JYD76SmnxEX58unWQnyhnA","review_count":425,"categories":[{"alias":"bars","title":"Bars"},{"alias":"tradamerican","title":"American"}],"rating":4.2,"coordinates":{"latitude":40.786692073145,"longitude":-73.9755653589964},"transactions":["pickup","delivery"],"price":"$$","location":{"address1":"511 Amsterdam Ave","address2":"","address3":"","city":"New York","zip_code":"10024","country":"US","state":"NY","display_address":["511 Amsterdam Ave","New York, NY 10024"]},"phone":"+12128770961","display_phone":"(212) 877-0961","distance":1461.2246925057527,"business_hours":[{"open":[{"is_overnight":false,"start":"1700","end":"2300","day":0},{"is_overnight":false,"start":"1700","end":"0000","day":1},{"is_overnight":false,"start":"1700","end":"0000","day":2},{"is_overnight":true,"start":"1600","end":"0200","day":3},{"is_overnight":true,"start":"1400","end":"0200","day":4},{"is_overnight":true,"start":"1200","end":"0200","day":5},{"is_overnight":false,"start":"1200","end":"2300","day":6}],"hours_type":"REGULAR","is_open_now":false}],"attributes":{"business_temp_closed":null,"menu_url":"https://m.emenu.me/index.html#/ba5a78562f7244e2839271b617258837","open24_hours":null,"waitlist_reservation":null}},{"id":"MH08_pIRKsUSwfkVYxUE7w","alias":"vinatería-new-york-5","name":"Vinatería","image_url":"https://s3-media2.fl.yelpcdn.com/bphoto/qDZdWOELDVu3OQs5qaAC0A/o.jpg","is_closed":false,"url":"https://www.yelp.com/biz/vinater%C3%ADa-new-york-5?adjust_creative=JYD76SmnxEX58unWQnyhnA&utm_campaign=yelp_api_v3&utm_medium=api_v3_business_search&utm_source=JYD76SmnxEX58unWQnyhnA","review_count":691,"categories":[{"alias":"italian","title":"Italian"},{"alias":"spanish","title":"Spanish"},{"alias":"mediterranean","title":"Mediterranean"}],"rating":3.9,"coordinates":{"latitude":40.806656523356345,"longitude":-73.95406344446592},"transactions":["pickup","delivery"],"price":"$$","location":{"address1":"2211 Frederick Douglass Blvd","address2":null,"address3":"","city":"New York","zip_code":"10026","country":"US","state":"NY","display_address":["2211 Frederick Douglass Blvd","New York, NY 10026"]},"phone":"+12126628462","display_phone":"(212) 662-8462","distance":1451.5355088513638,"business_hours":[{"open":[{"is_overnight":false,"start":"1700","end":"2200","day":0},{"is_overnight":false,"start":"1700","end":"2200","day":1},{"is_overnight":false,"start":"1700","end":"2200","day":2},{"is_overnight":false,"start":"1700","end":"2300","day":3},{"is_overnight":false,"start":"1700","end":"2300","day":4},{"is_overnight":false,"start":"1100","end":"2300","day":5},{"is_overnight":false,"start":"1100","end":"2200","day":6}],"hours_type":"REGULAR","is_open_now":false}],"attributes":{"business_temp_closed":null,"menu_url":"https://checkle.menu/vinateria_nyc","open24_hours":null,"waitlist_reservation":null}},{"id":"E9NMNWvV70HV5gB369N0EA","alias":"nerai-new-york","name":"Nerai","image_url":"https://s3-media2.fl.yelpcdn.com/bphoto/U5YSem3ON_yiTfzlsjKgYQ/o.jpg","is_closed":false,"url":"https://www.yelp.com/biz/nerai-new-york?adjust_creative=JYD76SmnxEX58unWQnyhnA&utm_campaign=yelp_api_v3&utm_medium=api_v3_business_search&utm_source=JYD76SmnxEX58unWQnyhnA","review_count":741,"categories":[{"alias":"greek","title":"Greek"},{"alias":"seafood","title":"Seafood"},{"alias":"mediterranean","title":"Mediterranean"}],"rating":4.4,"coordinates":{"latitude":40.7602650885775,"longitude":-73.97308862568121},"transactions":["pickup","delivery"],"price":"$$$","location":{"address1":"55 E 54th St","address2":null,"address3":"","city":"New York","zip_code":"10022","country":"US","state":"NY","display_address":["55 E 54th St","New York, NY 10022"]},"phone":"+12127595554","display_phone":"(212) 759-5554","distance":4248.4461886139,"business_hours":[{"open":[{"is_overnight":false,"start":"1130","end":"1430","day":0},{"is_overnight":false,"start":"1700","end":"2200","day":0},{"is_overnight":false,"start":"1130","end":"1430","day":1},{"is_overnight":false,"start":"1700","end":"2200","day":1},{"is_overnight":false,"start":"1130","end":"1430","day":2},{"is_overnight":false,"start":"1700","end":"2200","day":2},{"is_overnight":false,"start":"1130","end":"1430","day":3},{"is_overnight":false,"start":"1700","end":"2200","day":3},{"is_overnight":false,"start":"1130","end":"1430","day":4},{"is_overnight":false,"start":"1700","end":"2200","day":4},{"is_overnight":false,"start":"1700","end":"2200","day":5},{"is_overnight":false,"start":"1700","end":"2100","day":6}],"hours_type":"REGULAR","is_open_now":false}],"attributes":{"business_temp_closed":null,"menu_url":"https://nerainyc.com/menus/","open24_hours":null,"waitlist_reservation":true}},{"id":"XsXLVWr1UZWVhKThNvNiaA","alias":"blue-willow-夜来湘-new-york-2","name":"Blue Willow 夜来湘","image_url":"https://s3-media2.fl.yelpcdn.com/bphoto/1E59vOqmXZHBlJe0lLBHtA/o.jpg","is_closed":false,"url":"https://www.yelp.com/biz/blue-willow-%E5%A4%9C%E6%9D%A5%E6%B9%98-new-york-2?adjust_creative=JYD76SmnxEX58unWQnyhnA&utm_campaign=yelp_api_v3&utm_medium=api_v3_business_search&utm_source=JYD76SmnxEX58unWQnyhnA","review_count":1352,"categories":[{"alias":"szechuan","title":"Szechuan"}],"rating":4.4,"coordinates":{"latitude":40.76292,"longitude":-73.976546},"transactions":["pickup","delivery"],"location":{"address1":"40 W 56th St","address2":null,"address3":"","city":"New York","zip_code":"10019","country":"US","state":"NY","display_address":["40 W 56th St","New York, NY 10019"]},"phone":"+12122132299","display_phone":"(212) 213-2299","distance":3997.449710858242,"business_hours":[{"open":[{"is_overnight":false,"start":"1130","end":"2200","day":0},{"is_overnight":false,"start":"1130","end":"2200","day":1},{"is_overnight":false,"start":"1130","end":"2200","day":2},{"is_overnight":false,"start":"1130","end":"2200","day":3},{"is_overnight":false,"start":"1130","end":"2200","day":4},{"is_overnight":false,"start":"1200","end":"2200","day":5},{"is_overnight":false,"start":"1200","end":"2200","day":6}],"hours_type":"REGULAR","is_open_now":false}],"attributes":{"business_temp_closed":null,"menu_url":"https://www.bluewillownyc.com/food-menu","open24_hours":null,"waitlist_reservation":null}},{"id":"1DfbZ0VsSCg9g1KILmnvzQ","alias":"per-se-new-york","name":"Per Se","image_url":"https://s3-media1.fl.yelpcdn.com/bphoto/9r083qJDOAn9H3Q-vAQgHw/o.jpg","is_closed":false,"url":"https://www.yelp.com/biz/per-se-new-york?adjust_creative=JYD76SmnxEX58unWQnyhnA&utm_campaign=yelp_api_v3&utm_medium=api_v3_business_search&utm_source=JYD76SmnxEX58unWQnyhnA","review_count":1977,"categories":[{"alias":"french","title":"French"}],"rating":4.5,"coordinates":{"latitude":40.7681528889558,"longitude":-73.9827629623657},"transactions":[],"price":"$$$$","location":{"address1":"10 Columbus Cir","address2":"Fl 4","address3":null,"city":"New York","zip_code":"10019","country":"US","state":"NY","display_address":["10 Columbus Cir","Fl 4","New York, NY 10019"]},"phone":"+12128239335","display_phone":"(212) 823-9335","distance":3589.6853441359185,"business_hours":[{"open":[{"is_overnight":false,"start":"1630","end":"2030","day":0},{"is_overnight":false,"start":"1630","end":"2030","day":1},{"is_overnight":false,"start":"1630","end":"2030","day":2},{"is_overnight":false,"start":"1630","end":"2030","day":3},{"is_overnight":false,"start":"1630","end":"2030","day":4},{"is_overnight":false,"start":"1630","end":"2030","day":5},{"is_overnight":false,"start":"1630","end":"2030","day":6}],"hours_type":"REGULAR","is_open_now":false}],"attributes":{"business_temp_closed":null,"menu_url":"http://www.thomaskeller.com/new-york-new-york/per-se/todays-menus","open24_hours":null,"waitlist_reservation":null}},{"id":"AHrU1F123QPdVPTCnsy_xA","alias":"chalong-new-york","name":"Chalong","image_url":"https://s3-media1.fl.yelpcdn.com/bphoto/8NtN_x2cArNqRfG2ioh6qQ/o.jpg","is_closed":false,"url":"https://www.yelp.com/biz/chalong-new-york?adjust_creative=JYD76SmnxEX58unWQnyhnA&utm_campaign=yelp_api_v3&utm_medium=api_v3_business_search&utm_source=JYD76SmnxEX58unWQnyhnA","review_count":532,"categories":[{"alias":"thai","title":"Thai"}],"rating":4.6,"coordinates":{"latitude":40.763924,"longitude":-73.988883},"transactions":["pickup","delivery"],"price":"$$$","location":{"address1":"749 9th Ave","address2":"","address3":"","city":"New York","zip_code":"10019","country":"US","state":"NY","display_address":["749 9th Ave","New York, NY 10019"]},"phone":"+12124666456","display_phone":"(212) 466-6456","distance":4227.621955260953,"business_hours":[{"open":[{"is_overnight":false,"start":"1200","end":"1530","day":0},{"is_overnight":false,"start":"1700","end":"2200","day":0},{"is_overnight":false,"start":"1200","end":"1530","day":1},{"is_overnight":false,"start":"1700","end":"2200","day":1},{"is_overnight":false,"start":"1200","end":"1530","day":2},{"is_overnight":false,"start":"1700","end":"2200","day":2},{"is_overnight":false,"start":"1200","end":"1530","day":3},{"is_overnight":false,"start":"1700","end":"2200","day":3},{"is_overnight":false,"start":"1200","end":"1530","day":4},{"is_overnight":false,"start":"1700","end":"2300","day":4},{"is_overnight":false,"start":"1200","end":"1530","day":5},{"is_overnight":false,"start":"1700","end":"2300","day":5},{"is_overnight":false,"start":"1200","end":"1530","day":6},{"is_overnight":false,"start":"1700","end":"2200","day":6}],"hours_type":"REGULAR","is_open_now":false}],"attributes":{"business_temp_closed":null,"menu_url":"https://www.chalongnyc.com/menus","open24_hours":null,"waitlist_reservation":null}},{"id":"_JIidp30qxD3bfpP3DSMTA","alias":"taverna-veranda-edgewater","name":"Taverna Veranda","image_url":"https://s3-media2.fl.yelpcdn.com/bphoto/7lxh_Y9LYH2GfCSuueAiAw/o.jpg","is_closed":false,"url":"https://www.yelp.com/biz/taverna-veranda-edgewater?adjust_creative=JYD76SmnxEX58unWQnyhnA&utm_campaign=yelp_api_v3&utm_medium=api_v3_business_search&utm_source=JYD76SmnxEX58unWQnyhnA","review_count":275,"categories":[{"alias":"mediterranean","title":"Mediterranean"}],"rating":4,"coordinates":{"latitude":40.81899409072942,"longitude":-73.9766440675938},"transactions":["pickup","delivery"],"price":"$$$","location":{"address1":"725 River Rd","address2":"","address3":null,"city":"Edgewater","zip_code":"07020","country":"US","state":"NJ","display_address":["725 River Rd","Edgewater, NJ 07020"]},"phone":"+12018301650","display_phone":"(201) 830-1650","distance":2443.271757570312,"business_hours":[{"open":[{"is_overnight":false,"start":"1700","end":"2200","day":0},{"is_overnight":false,"start":"1700","end":"2200","day":1},{"is_overnight":false,"start":"1700","end":"2200","day":2},{"is_overnight":false,"start":"1700","end":"2200","day":3},{"is_overnight":false,"start":"1700","end":"2300","day":4},{"is_overnight":false,"start":"1700","end":"2300","day":5},{"is_overnight":false,"start":"1200","end":"1600","day":6},{"is_overnight":false,"start":"1700","end":"2200","day":6}],"hours_type":"REGULAR","is_open_now":false}],"attributes":{"business_temp_closed":null,"menu_url":null,"open24_hours":null,"waitlist_reservation":null}},{"id":"_CkPo7EqIELNiUWAPHfi1Q","alias":"the-good-good-new-york","name":"The Good Good","image_url":"https://s3-media2.fl.yelpcdn.com/bphoto/cZf9CoJFxhlBZM6P74K0xg/o.jpg","is_closed":false,"url":"https://www.yelp.com/biz/the-good-good-new-york?adjust_creative=JYD76SmnxEX58unWQnyhnA&utm_campaign=yelp_api_v3&utm_medium=api_v3_business_search&utm_source=JYD76SmnxEX58unWQnyhnA","review_count":86,"categories":[{"alias":"newamerican","title":"New American"},{"alias":"lounges","title":"Lounges"},{"alias":"cocktailbars","title":"Cocktail Bars"}],"rating":4.7,"coordinates":{"latitude":40.801282,"longitude":-73.942263},"transactions":[],"location":{"address1":"1694 Park Ave","address2":"","address3":null,"city":"New York","zip_code":"10035","country":"US","state":"NY","display_address":["1694 Park Ave","New York, NY 10035"]},"phone":"+19174090103","display_phone":"(917) 409-0103","distance":2130.437118052621,"business_hours":[{"open":[{"is_overnight":false,"start":"1700","end":"0000","day":0},{"is_overnight":false,"start":"1700","end":"0000","day":1},{"is_overnight":false,"start":"1700","end":"0000","day":2},{"is_overnight":false,"start":"1700","end":"0000","day":3},{"is_overnight":true,"start":"1700","end":"0100","day":4},{"is_overnight":true,"start":"1100","end":"0100","day":5},{"is_overnight":false,"start":"1100","end":"0000","day":6}],"hours_type":"REGULAR","is_open_now":true}],"attributes":{"business_temp_closed":null,"menu_url":"https://www.thegoodgoodnyc.com/menu","open24_hours":null,"waitlist_reservation":null}},{"id":"7hh2eP4HVkyjtpcqeITk3Q","alias":"ollies-noodle-shop-and-grille-new-york","name":"Ollie's Noodle Shop & Grille","image_url":"https://s3-media2.fl.yelpcdn.com/bphoto/wnGISC3H98-K7T-rkOesOw/o.jpg","is_closed":false,"url":"https://www.yelp.com/biz/ollies-noodle-shop-and-grille-new-york?adjust_creative=JYD76SmnxEX58unWQnyhnA&utm_campaign=yelp_api_v3&utm_medium=api_v3_business_search&utm_source=JYD76SmnxEX58unWQnyhnA","review_count":248,"categories":[{"alias":"chinese","title":"Chinese"},{"alias":"noodles","title":"Noodles"},{"alias":"hotdogs","title":"Fast Food"}],"rating":3.1,"coordinates":{"latitude":40.79942,"longitude":-73.96868},"transactions":["pickup","delivery"],"price":"$$","location":{"address1":"2705 Broadway","address2":"","address3":"","city":"New York","zip_code":"10025","country":"US","state":"NY","display_address":["2705 Broadway","New York, NY 10025"]},"phone":"+12129323300","display_phone":"(212) 932-3300","distance":188.44711986593697,"business_hours":[{"open":[{"is_overnight":false,"start":"1130","end":"2200","day":0},{"is_overnight":false,"start":"1130","end":"2200","day":1},{"is_overnight":false,"start":"1130","end":"2200","day":2},{"is_overnight":false,"start":"1130","end":"2200","day":3},{"is_overnight":false,"start":"1130","end":"2200","day":4},{"is_overnight":false,"start":"1130","end":"2200","day":5},{"is_overnight":false,"start":"1130","end":"2200","day":6}],"hours_type":"REGULAR","is_open_now":false}],"attributes":{"business_temp_closed":null,"menu_url":"","open24_hours":null,"waitlist_reservation":null}},{"id":"w4aW7geanPgny-dxsDNkMA","alias":"moon-kee-new-york","name":"Moon Kee","image_url":"https://s3-media3.fl.yelpcdn.com/bphoto/mBFi4kOOhvBE2s8ceoZwDQ/o.jpg","is_closed":false,"url":"https://www.yelp.com/biz/moon-kee-new-york?adjust_creative=JYD76SmnxEX58unWQnyhnA&utm_campaign=yelp_api_v3&utm_medium=api_v3_business_search&utm_source=JYD76SmnxEX58unWQnyhnA","review_count":90,"categories":[{"alias":"cantonese","title":"Cantonese"},{"alias":"dimsum","title":"Dim Sum"},{"alias":"hkcafe","title":"Hong Kong Style Cafe"}],"rating":4.2,"coordinates":{"latitude":40.7973721,"longitude":-73.9694833},"transactions":["pickup","delivery"],"price":"$$","location":{"address1":"2642 Broadway","address2":"","address3":null,"city":"New York","zip_code":"10025","country":"US","state":"NY","display_address":["2642 Broadway","New York, NY 10025"]},"phone":"+16464389283","display_phone":"(646) 438-9283","distance":212.5917817836332,"business_hours":[{"open":[{"is_overnight":false,"start":"1130","end":"2200","day":0},{"is_overnight":false,"start":"1130","end":"2200","day":1},{"is_overnight":false,"start":"1130","end":"2200","day":2},{"is_overnight":false,"start":"1130","end":"2200","day":3},{"is_overnight":false,"start":"1130","end":"2200","day":4},{"is_overnight":false,"start":"1100","end":"2200","day":5},{"is_overnight":false,"start":"1100","end":"2200","day":6}],"hours_type":"REGULAR","is_open_now":false}],"attributes":{"business_temp_closed":null,"menu_url":"https://moonkeerestaurant.com/menu/","open24_hours":null,"waitlist_reservation":null}},{"id":"J9xVQScnr0lYWl61_mLXMA","alias":"lido-new-york","name":"Lido","image_url":"https://s3-media3.fl.yelpcdn.com/bphoto/9cGpi2mEcBqzRy8vUJiwwQ/o.jpg","is_closed":false,"url":"https://www.yelp.com/biz/lido-new-york?adjust_creative=JYD76SmnxEX58unWQnyhnA&utm_campaign=yelp_api_v3&utm_medium=api_v3_business_search&utm_source=JYD76SmnxEX58unWQnyhnA","review_count":1271,"categories":[{"alias":"italian","title":"Italian"},{"alias":"breakfast_brunch","title":"Breakfast & Brunch"},{"alias":"cocktailbars","title":"Cocktail Bars"}],"rating":4.1,"coordinates":{"latitude":40.8049797781916,"longitude":-73.9548260014624},"transactions":["delivery"],"price":"$$","location":{"address1":"2168 Frederick Douglass Blvd","address2":"","address3":"","city":"New York","zip_code":"10026","country":"US","state":"NY","display_address":["2168 Frederick Douglass Blvd","New York, NY 10026"]},"phone":"+16464908575","display_phone":"(646) 490-8575","distance":1285.9418349273824,"business_hours":[{"open":[{"is_overnight":false,"start":"1200","end":"2200","day":0},{"is_overnight":false,"start":"1200","end":"2200","day":1},{"is_overnight":false,"start":"1200","end":"2200","day":2},{"is_overnight":false,"start":"1200","end":"2200","day":3},{"is_overnight":false,"start":"1200","end":"2200","day":4},{"is_overnight":false,"start":"1030","end":"2200","day":5},{"is_overnight":false,"start":"1030","end":"2200","day":6}],"hours_type":"REGULAR","is_open_now":false}],"attributes":{"business_temp_closed":null,"menu_url":"http://www.lidoharlem.com/","open24_hours":null,"waitlist_reservation":null}},{"id":"4KzqwQus39gXgrwrDXAjWA","alias":"eléa-new-york","name":"Eléa","image_url":"https://s3-media2.fl.yelpcdn.com/bphoto/brsHqnQddXSNAa_cpPk69g/o.jpg","is_closed":false,"url":"https://www.yelp.com/biz/el%C3%A9a-new-york?adjust_creative=JYD76SmnxEX58unWQnyhnA&utm_campaign=yelp_api_v3&utm_medium=api_v3_business_search&utm_source=JYD76SmnxEX58unWQnyhnA","review_count":363,"categories":[{"alias":"mediterranean","title":"Mediterranean"},{"alias":"greek","title":"Greek"},{"alias":"seafood","title":"Seafood"}],"rating":4.3,"coordinates":{"latitude":40.78754,"longitude":-73.9765199},"transactions":["pickup","delivery"],"price":"$$$","location":{"address1":"217 W 85th St","address2":"","address3":null,"city":"New York","zip_code":"10024","country":"US","state":"NY","display_address":["217 W 85th St","New York, NY 10024"]},"phone":"+12123699800","display_phone":"(212) 369-9800","distance":1415.2650781101029,"business_hours":[{"open":[{"is_overnight":false,"start":"1700","end":"2130","day":0},{"is_overnight":false,"start":"1700","end":"2130","day":1},{"is_overnight":false,"start":"1700","end":"2130","day":2},{"is_overnight":false,"start":"1700","end":"2200","day":3},{"is_overnight":false,"start":"1130","end":"1500","day":4},{"is_overnight":false,"start":"1700","end":"2200","day":4},{"is_overnight":false,"start":"1130","end":"1500","day":5},{"is_overnight":false,"start":"1630","end":"2200","day":5},{"is_overnight":false,"start":"1130","end":"1500","day":6},{"is_overnight":false,"start":"1630","end":"2100","day":6}],"hours_type":"REGULAR","is_open_now":false}],"attributes":{"business_temp_closed":null,"menu_url":"https://eleanyc.com/new-york-upper-west-side-elea-food-menu","open24_hours":null,"waitlist_reservation":true}},{"id":"z28cRtpdfiJfzIp1vkMAwQ","alias":"koko-wings-new-york-5","name":"Koko Wings","image_url":"https://s3-media3.fl.yelpcdn.com/bphoto/h1kyzQTYPQu923EJuV9DYQ/o.jpg","is_closed":false,"url":"https://www.yelp.com/biz/koko-wings-new-york-5?adjust_creative=JYD76SmnxEX58unWQnyhnA&utm_campaign=yelp_api_v3&utm_medium=api_v3_business_search&utm_source=JYD76SmnxEX58unWQnyhnA","review_count":443,"categories":[{"alias":"korean","title":"Korean"},{"alias":"chicken_wings","title":"Chicken Wings"},{"alias":"chickenshop","title":"Chicken Shop"}],"rating":3.7,"coordinates":{"latitude":40.80096,"longitude":-73.96734},"transactions":["pickup","delivery"],"price":"$$","location":{"address1":"248 W 106th St","address2":null,"address3":"","city":"New York","zip_code":"10025","country":"US","state":"NY","display_address":["248 W 106th St","New York, NY 10025"]},"phone":"+12129327722","display_phone":"(212) 932-7722","distance":304.754771512852,"business_hours":[{"open":[{"is_overnight":false,"start":"1100","end":"2330","day":0},{"is_overnight":false,"start":"1100","end":"2200","day":1},{"is_overnight":false,"start":"1100","end":"2330","day":2},{"is_overnight":false,"start":"1100","end":"2330","day":3},{"is_overnight":false,"start":"1100","end":"0000","day":4},{"is_overnight":false,"start":"1100","end":"0000","day":5},{"is_overnight":false,"start":"1100","end":"2330","day":6}],"hours_type":"REGULAR","is_open_now":true}],"attributes":{"business_temp_closed":null,"menu_url":"https://www.kokowingsnyc.com/upper-west-side-menu/","open24_hours":null,"waitlist_reservation":null}},{"id":"6NcU2JAznLr9dDHp6GgQyw","alias":"doaba-deli-new-york-2","name":"Doaba Deli","image_url":"https://s3-media1.fl.yelpcdn.com/bphoto/0go3o0EwYkjgIzM0rf-xUQ/o.jpg","is_closed":false,"url":"https://www.yelp.com/biz/doaba-deli-new-york-2?adjust_creative=JYD76SmnxEX58unWQnyhnA&utm_campaign=yelp_api_v3&utm_medium=api_v3_business_search&utm_source=JYD76SmnxEX58unWQnyhnA","review_count":258,"categories":[{"alias":"indpak","title":"Indian"},{"alias":"pakistani","title":"Pakistani"},{"alias":"bangladeshi","title":"Bangladeshi"}],"rating":4.5,"coordinates":{"latitude":40.7994,"longitude":-73.962402},"transactions":["pickup","delivery"],"price":"$","location":{"address1":"945 Columbus Ave","address2":"","address3":"","city":"New York","zip_code":"10025","country":"US","state":"NY","display_address":["945 Columbus Ave","New York, NY 10025"]},"phone":"+12122222636","display_phone":"(212) 222-2636","distance":425.0083739117874,"business_hours":[{"open":[{"is_overnight":false,"start":"1000","end":"0000","day":0},{"is_overnight":false,"start":"1000","end":"0000","day":1},{"is_overnight":false,"start":"1000","end":"0000","day":2},{"is_overnight":false,"start":"1000","end":"0000","day":3},{"is_overnight":false,"start":"1000","end":"0000","day":4},{"is_overnight":false,"start":"1000","end":"0000","day":5},{"is_overnight":false,"start":"1000","end":"0000","day":6}],"hours_type":"REGULAR","is_open_now":true}],"attributes":{"business_temp_closed":null,"menu_url":null,"open24_hours":null,"waitlist_reservation":null}},{"id":"3eBV6HwWcdHzJW3sUH-2hw","alias":"ichiran-times-square-new-york-4","name":"ICHIRAN - Times Square","image_url":"https://s3-media2.fl.yelpcdn.com/bphoto/hdYDb0fN3Wn17xJU5TM9Tg/o.jpg","is_closed":false,"url":"https://www.yelp.com/biz/ichiran-times-square-new-york-4?adjust_creative=JYD76SmnxEX58unWQnyhnA&utm_campaign=yelp_api_v3&utm_medium=api_v3_business_search&utm_source=JYD76SmnxEX58unWQnyhnA","review_count":1135,"categories":[{"alias":"ramen","title":"Ramen"},{"alias":"noodles","title":"Noodles"},{"alias":"desserts","title":"Desserts"}],"rating":4.4,"coordinates":{"latitude":40.7600737531204,"longitude":-73.9833259411037},"transactions":["pickup","delivery"],"price":"$$","location":{"address1":"152 W 49th St","address2":null,"address3":"","city":"New York","zip_code":"10019","country":"US","state":"NY","display_address":["152 W 49th St","New York, NY 10019"]},"phone":"+16469644294","display_phone":"(646) 964-4294","distance":4452.520968121275,"business_hours":[{"open":[{"is_overnight":false,"start":"1100","end":"2200","day":0},{"is_overnight":false,"start":"1100","end":"2200","day":1},{"is_overnight":false,"start":"1100","end":"2200","day":2},{"is_overnight":false,"start":"1100","end":"2200","day":3},{"is_overnight":false,"start":"1100","end":"2200","day":4},{"is_overnight":false,"start":"1100","end":"2200","day":5},{"is_overnight":false,"start":"1100","end":"2200","day":6}],"hours_type":"REGULAR","is_open_now":false}],"attributes":{"business_temp_closed":null,"menu_url":"https://www.ichiranusa.com/menu/","open24_hours":null,"waitlist_reservation":null}},{"id":"_LJFf9YqpYxvExTvVxb7Rw","alias":"the-modern-new-york-3","name":"The Modern","image_url":"https://s3-media3.fl.yelpcdn.com/bphoto/jWYFAgxkZ-Y7sFIr29mDIQ/o.jpg","is_closed":false,"url":"https://www.yelp.com/biz/the-modern-new-york-3?adjust_creative=JYD76SmnxEX58unWQnyhnA&utm_campaign=yelp_api_v3&utm_medium=api_v3_business_search&utm_source=JYD76SmnxEX58unWQnyhnA","review_count":1261,"categories":[{"alias":"newamerican","title":"New American"}],"rating":4.3,"coordinates":{"latitude":40.761106128269006,"longitude":-73.97670872686992},"transactions":["pickup"],"price":"$$$$","location":{"address1":"9 W 53rd St","address2":"","address3":"","city":"New York","zip_code":"10019","country":"US","state":"NY","display_address":["9 W 53rd St","New York, NY 10019"]},"phone":"+12123331220","display_phone":"(212) 333-1220","distance":4202.764318419553,"business_hours":[{"open":[{"is_overnight":false,"start":"1200","end":"1400","day":0},{"is_overnight":false,"start":"1730","end":"2100","day":0},{"is_overnight":false,"start":"1200","end":"1400","day":1},{"is_overnight":false,"start":"1730","end":"2100","day":1},{"is_overnight":false,"start":"1200","end":"1400","day":2},{"is_overnight":false,"start":"1730","end":"2100","day":2},{"is_overnight":false,"start":"1200","end":"1400","day":3},{"is_overnight":false,"start":"1730","end":"2100","day":3},{"is_overnight":false,"start":"1200","end":"1400","day":4},{"is_overnight":false,"start":"1700","end":"2100","day":4},{"is_overnight":false,"start":"1200","end":"1400","day":5},{"is_overnight":false,"start":"1700","end":"2100","day":5},{"is_overnight":false,"start":"1200","end":"1400","day":6}],"hours_type":"REGULAR","is_open_now":false}],"attributes":{"business_temp_closed":null,"menu_url":null,"open24_hours":null,"waitlist_reservation":null}},{"id":"3vBVnzsJLRh8WtW3awKxeQ","alias":"bodega-88-new-york","name":"Bodega 88","image_url":"https://s3-media4.fl.yelpcdn.com/bphoto/MiCgwf8rqKsy3vILQbIt-A/o.jpg","is_closed":false,"url":"https://www.yelp.com/biz/bodega-88-new-york?adjust_creative=JYD76SmnxEX58unWQnyhnA&utm_campaign=yelp_api_v3&utm_medium=api_v3_business_search&utm_source=JYD76SmnxEX58unWQnyhnA","review_count":252,"categories":[{"alias":"sportsbars","title":"Sports Bars"},{"alias":"cocktailbars","title":"Cocktail Bars"},{"alias":"latin","title":"Latin American"}],"rating":4.3,"coordinates":{"latitude":40.7875358759796,"longitude":-73.9711353555322},"transactions":["pickup","delivery"],"price":"$$","location":{"address1":"573 Columbus Ave","address2":"","address3":null,"city":"New York","zip_code":"10024","country":"US","state":"NY","display_address":["573 Columbus Ave","New York, NY 10024"]},"phone":"+12127991602","display_phone":"(212) 799-1602","distance":1232.212543254116,"business_hours":[{"open":[{"is_overnight":false,"start":"1200","end":"0000","day":0},{"is_overnight":false,"start":"1200","end":"0000","day":1},{"is_overnight":false,"start":"1200","end":"0000","day":2},{"is_overnight":false,"start":"1200","end":"0000","day":3},{"is_overnight":false,"start":"1200","end":"0000","day":4},{"is_overnight":false,"start":"1200","end":"0000","day":5},{"is_overnight":false,"start":"1200","end":"0000","day":6}],"hours_type":"REGULAR","is_open_now":true}],"attributes":{"business_temp_closed":null,"menu_url":"http://www.bodega88nyc.com/wp-content/uploads/2016/09/menu-9-14.pdf","open24_hours":null,"waitlist_reservation":null}},{"id":"X83qWL5WPR-QWGXGQ8WP-Q","alias":"nr-new-york-4","name":"NR","image_url":"https://s3-media1.fl.yelpcdn.com/bphoto/NrvoCASQCrkzYH3tJvE76g/o.jpg","is_closed":false,"url":"https://www.yelp.com/biz/nr-new-york-4?adjust_creative=JYD76SmnxEX58unWQnyhnA&utm_campaign=yelp_api_v3&utm_medium=api_v3_business_search&utm_source=JYD76SmnxEX58unWQnyhnA","review_count":418,"categories":[{"alias":"ramen","title":"Ramen"},{"alias":"seafood","title":"Seafood"},{"alias":"cocktailbars","title":"Cocktail Bars"}],"rating":4.5,"coordinates":{"latitude":40.770153,"longitude":-73.954956},"transactions":["pickup","delivery"],"price":"$$$","location":{"address1":"339 E 75th St","address2":"","address3":null,"city":"New York","zip_code":"10021","country":"US","state":"NY","display_address":["339 E 75th St","New York, NY 10021"]},"phone":"+16462264874","display_phone":"(646) 226-4874","distance":3290.5090744387207,"business_hours":[{"open":[{"is_overnight":false,"start":"1700","end":"2300","day":0},{"is_overnight":false,"start":"1700","end":"2300","day":1},{"is_overnight":false,"start":"1700","end":"2300","day":2},{"is_overnight":false,"start":"1700","end":"0000","day":3},{"is_overnight":false,"start":"1700","end":"0000","day":4},{"is_overnight":false,"start":"1200","end":"0000","day":5},{"is_overnight":false,"start":"1200","end":"2200","day":6}],"hours_type":"REGULAR","is_open_now":false}],"attributes":{"business_temp_closed":null,"menu_url":"http://www.nr-nyc.com/assets/menu/full-menu-1.pdf","open24_hours":null,"waitlist_reservation":null}}]